mp4viewer/__init__.py
mp4viewer/__main__.py
mp4viewer/console.py
mp4viewer/datasource.py
mp4viewer/gui.py
mp4viewer/json_renderer.py
mp4viewer/tree.py
mp4viewer/isobmff/__init__.py
mp4viewer/isobmff/box.py
mp4viewer/isobmff/cenc.py
mp4viewer/isobmff/flv.py
mp4viewer/isobmff/fragment.py
mp4viewer/isobmff/movie.py
mp4viewer/isobmff/parser.py
mp4viewer/isobmff/utils.py
mp4viewer-0.1.2.dist-info/METADATA
mp4viewer-0.1.2.dist-info/WHEEL
mp4viewer-0.1.2.dist-info/licenses/LICENSE
mp4viewer-0.1.2.dist-info/RECORD
