Metadata-Version: 2.3
Name: mp4viewer
Version: 0.1.2
Summary: Parse mp4 files and inspect their metadata
Project-URL: Homepage, https://github.com/amarghosh/mp4viewer
Project-URL: Issues, https://github.com/amarghosh/mp4viewer/issues
Author-email: Amarghosh Vadakkoot <myfirstname@gmail.com>
License-File: LICENSE
Classifier: License :: OSI Approved :: MIT License
Classifier: Operating System :: OS Independent
Classifier: Programming Language :: Python :: 3
Requires-Python: >=3.8
